ProteinTokenizer/__init__.py
ProteinTokenizer-0.1.dist-info/License.txt
ProteinTokenizer-0.1.dist-info/METADATA
ProteinTokenizer-0.1.dist-info/WHEEL
ProteinTokenizer-0.1.dist-info/top_level.txt
ProteinTokenizer-0.1.dist-info/RECORD
