Metadata-Version: 2.1
Name: ProteinTokenizer
Version: 0.1
Summary: Tokenization of protein sequence at the Amino acid level.
Author: Rainear Mendez
Author-email: rainearmendez@cmu.edu.ph
Classifier: Programming Language :: Python :: 3
Classifier: License :: OSI Approved :: MIT License
Classifier: Operating System :: OS Independent
License-File: License.txt
